{
    "version": "2.5.7",
    "description": "Command line interface to LiveKit",
    "homepage": "https://github.com/livekit/livekit-cli",
    "license": "Apache",
    "url": "https://github.com/livekit/livekit-cli/releases/download/v2.5.7/lk_2.5.7_windows_amd64.zip",
    "hash": "fcf5f2f1205948600f5fa1b770d0b1dcfc81d14c8c92dff1656c4bfbeca130ef",
    "bin": "lk.exe",
    "checkver": "github",
    "autoupdate": {
        "url": "https://github.com/livekit/livekit-cli/releases/download/v$version/lk_$version_windows_amd64.zip"
    }
}
